vjwhats/__init__.py
vjwhats/whatsapp.py
vjwhats-1.1.dist-info/LICENSE
vjwhats-1.1.dist-info/METADATA
vjwhats-1.1.dist-info/WHEEL
vjwhats-1.1.dist-info/top_level.txt
vjwhats-1.1.dist-info/RECORD
