Metadata-Version: 2.1
Name: vjwhats
Version: 1.1
Summary: A Python library to interact with WhatsApp Web using Selenium.
Home-page: https://github.com/Fioruci/vjwhats
Author: Fioruci
Author-email: fiorucit@gmail.com
Classifier: Programming Language :: Python :: 3
Classifier: License :: OSI Approved :: MIT License
Classifier: Operating System :: OS Independent
Requires-Python: >=3.12
License-File: LICENSE
Requires-Dist: selenium >=4.0
